CHANGES.txt
MANIFEST.in
README.rst
setup.py
bin/region_analysis.py
regionanalysis/__init__.py
regionanalysis/database/README.MD
regionanalysis/database/hg19.ensembl.biotype_region_ext.bed
regionanalysis/database/hg19.genome
regionanalysis/database/hg19.refseq.biotype_region_ext.bed
regionanalysis/database/hg19_genedeserts.bed
regionanalysis/database/hg19_pericentromeres.bed
regionanalysis/database/hg19_subtelomeres.bed
regionanalysis/database/mm10.ensembl.biotype.bed
regionanalysis/database/mm10.ensembl.biotype_region_ext.bed
regionanalysis/database/mm10.genome
regionanalysis/database/mm10.refseq.biotype.bed
regionanalysis/database/mm10.refseq.biotype_region_ext.bed
regionanalysis/database/mm10_geneDesert.bed
regionanalysis/database/mm10_pericentromere.bed
regionanalysis/database/mm10_subtelomere.bed
regionanalysis/database/mm9.ensembl.biotype_region_ext.bed
regionanalysis/database/mm9.genome
regionanalysis/database/mm9.refseq.biotype_region_ext.bed
regionanalysis/database/mm9_geneDesert.bed
regionanalysis/database/mm9_pericentromere.bed
regionanalysis/database/mm9_subtelomere.bed
regionanalysis/database/rn4.ensembl.biotype_region_ext.bed
regionanalysis/database/rn4.genome
regionanalysis/database/rn4.refseq.biotype_region_ext.bed
regionanalysis/database/rn4_genedeserts.bed
regionanalysis/database/rn4_pericentromeres.bed
regionanalysis/database/rn4_subtelomeres.bed
regionanalysis/example/test_with_header.bed
regionanalysis/example/test_with_header.bed.annotated.out
regionanalysis/example/test_with_header.bed.full.annotated.json.out
regionanalysis/example/test_with_header.bed.full.annotated.out
regionanalysis/example/test_without_header.bed
regionanalysis/example/test_without_header.bed.annotated.out
regionanalysis/example/test_without_header.bed.full.annotated.json.out
regionanalysis/example/test_without_header.bed.full.annotated.out
regionanalysis/exceptions/0.bed
regionanalysis/exceptions/1.bed
regionanalysis/exceptions/2.bed