Metadata-Version: 1.0
Name: regionanalysis
Version: 0.1.1
Summary: A utility to annotate genomic intervals.
Home-page: http://github.com/shenlab-sinai/region_analysis
Author: Ning-Yi SHAO
Author-email: shaoningyi@gmail.com
License: GPLv3
Platform: UNKNOWN
